CHANGELOG.rst
MANIFEST.in
README.rst
setup.cfg
setup.py
TwonicornWeb.egg-info/PKG-INFO
TwonicornWeb.egg-info/SOURCES.txt
TwonicornWeb.egg-info/dependency_links.txt
TwonicornWeb.egg-info/entry_points.txt
TwonicornWeb.egg-info/not-zip-safe
TwonicornWeb.egg-info/requires.txt
TwonicornWeb.egg-info/top_level.txt
twonicornweb/__init__.py
twonicornweb/models.py
twonicornweb/tests.py
twonicornweb/db/twonicorn-data.sql
twonicornweb/db/twonicorn-schema.sql
twonicornweb/static/additional-methods.min.js
twonicornweb/static/dev-jquery-2.1.3.min.js
twonicornweb/static/favico.png
twonicornweb/static/invalid.png
twonicornweb/static/jquery-2.1.3.min.js
twonicornweb/static/jquery.validate.min.js
twonicornweb/static/loading.gif
twonicornweb/static/logo.jpg
twonicornweb/static/logo_large.gif
twonicornweb/static/logo_large.jpg
twonicornweb/static/logo_medium.gif
twonicornweb/static/logo_mini.gif
twonicornweb/static/logo_small.gif
twonicornweb/static/nav-l.gif
twonicornweb/static/nav-le.gif
twonicornweb/static/nav-r.gif
twonicornweb/static/nav-re.gif
twonicornweb/static/pyramid-16x16.png
twonicornweb/static/pyramid.png
twonicornweb/static/red_asterisk.png
twonicornweb/static/row_expansion_app.js
twonicornweb/static/row_expansion_group.js
twonicornweb/static/tc.css
twonicornweb/static/test.css
twonicornweb/static/theme.min.css
twonicornweb/static/valid.png
twonicornweb/templates/api.pt
twonicornweb/templates/applications.pt
twonicornweb/templates/cp.pt
twonicornweb/templates/cp_application.pt
twonicornweb/templates/cp_deploy.pt
twonicornweb/templates/cp_group.pt
twonicornweb/templates/cp_user.pt
twonicornweb/templates/deploys.pt
twonicornweb/templates/exception.pt
twonicornweb/templates/forbidden.pt
twonicornweb/templates/global_layout.pt
twonicornweb/templates/group.pt
twonicornweb/templates/healthcheck.pt
twonicornweb/templates/help.pt
twonicornweb/templates/home.pt
twonicornweb/templates/login.pt
twonicornweb/templates/logout.pt
twonicornweb/templates/promote.pt
twonicornweb/templates/ss.pt
twonicornweb/templates/test.pt
twonicornweb/templates/user.pt
twonicornweb/views/__init__.py
twonicornweb/views/api.py
twonicornweb/views/applications.py
twonicornweb/views/cp.py
twonicornweb/views/cp_application.py
twonicornweb/views/cp_group.py
