Metadata-Version: 1.1
Name: TwonicornWeb
Version: 3.1
Summary: Twonicorn web api/ui
Home-page: https://github.com/CityGrid/twonicorn
Author: Aaron Bandt
Author-email: aaron.bandt@citygridmedia.com
License: Apache
Keywords: Twonicorn devops automation software deployment
Platform: UNKNOWN
Classifier: Programming Language :: Python
Classifier: Framework :: Pyramid
Classifier: Topic :: Internet :: WWW/HTTP
Classifier: Topic :: Internet :: WWW/HTTP :: WSGI :: Application
